i_principal_central_link/__init__.py
i_principal_central_link/core.py
i_principal_central_link/.venv/pyvenv.cfg
i_principal_central_link/.venv/bin/Activate.ps1
i_principal_central_link/.venv/bin/activate
i_principal_central_link/.venv/bin/activate.csh
i_principal_central_link/.venv/bin/activate.fish
i_principal_central_link/.venv/bin/pip
i_principal_central_link/.venv/bin/pip3
i_principal_central_link/.venv/bin/pip3.12
i_principal_central_link/.venv/bin/python
i_principal_central_link/.venv/bin/python3
i_principal_central_link/.venv/bin/python3.12
i_principal_central_link/.venv/lib/python3.12/site-packages/pip/__init__.py
i_principal_central_link/.venv/lib/python3.12/site-packages/pip/__main__.py
i_principal_central_link/.venv/lib/python3.12/site-packages/pip/__pip-runner__.py
i_principal_central_link/.venv/lib/python3.12/site-packages/pip/py.typed
i_principal_central_link/.venv/lib/python3.12/site-packages/pip/_internal/__init__.py
i_principal_central_link/.venv/lib/python3.12/site-packages/pip/_internal/build_env.py
i_principal_central_link/.venv/lib/python3.12/site-packages/pip/_internal/cache.py
i_principal_central_link/.venv/lib/python3.12/site-packages/pip/_internal/configuration.py
i_principal_central_link/.venv/lib/python3.12/site-packages/pip/_internal/exceptions.py
i_principal_central_link/.venv/lib/python3.12/site-packages/pip/_internal/main.py
i_principal_central_link/.venv/lib/python3.12/site-packages/pip/_internal/pyproject.py
i_principal_central_link/.venv/lib/python3.12/site-packages/pip/_internal/self_outdated_check.py
i_principal_central_link/.venv/lib/python3.12/site-packages/pip/_internal/wheel_builder.py
i_principal_central_link/.venv/lib/python3.12/site-packages/pip/_internal/cli/__init__.py
i_principal_central_link/.venv/lib/python3.12/site-packages/pip/_internal/cli/autocompletion.py
i_principal_central_link/.venv/lib/python3.12/site-packages/pip/_internal/cli/base_command.py
i_principal_central_link/.venv/lib/python3.12/site-packages/pip-24.0.dist-info/AUTHORS.txt
i_principal_central_link/.venv/lib/python3.12/site-packages/pip-24.0.dist-info/INSTALLER
i_principal_central_link/.venv/lib/python3.12/site-packages/pip-24.0.dist-info/LICENSE.txt
i_principal_central_link/.venv/lib/python3.12/site-packages/pip-24.0.dist-info/METADATA
i_principal_central_link/.venv/lib/python3.12/site-packages/pip-24.0.dist-info/RECORD
i_principal_central_link/.venv/lib/python3.12/site-packages/pip-24.0.dist-info/REQUESTED
i_principal_central_link/.venv/lib/python3.12/site-packages/pip-24.0.dist-info/WHEEL
i_principal_central_link/.venv/lib/python3.12/site-packages/pip-24.0.dist-info/entry_points.txt
i_principal_central_link/.venv/lib/python3.12/site-packages/pip-24.0.dist-info/top_level.txt
i_principal_central_link-0.1.3.dist-info/LICENSE
i_principal_central_link-0.1.3.dist-info/WHEEL
i_principal_central_link-0.1.3.dist-info/METADATA
i_principal_central_link-0.1.3.dist-info/RECORD
