Metadata-Version: 2.1
Name: i_principal_central_link
Version: 0.1.3
Summary: i simple Python library
Author-email: i_principal_central <deboubil24@gmail.com>
Requires-Python: >=3.7
